source/fft2.v
module fft2(
	input [31:0]xr,
	input [31:0]xi,
	input [31:0]yr,
	input [31:0]yi,
	output [31:0]Xr,
	output [31:0]Xi,
	output [31:0]Yr,
	output [31:0]Yi);

assign Xr = xr + yr;
assign Yr = xr - yr;
assign Xi = xi + yi;
assign Yi = xi - yi;
endmodule

source/complex_mul.v
module complex_mul(
	input signed [31:0]Xr,
	input signed [31:0]Xi,
	input signed [31:0]Yr,
	input signed [31:0]Yi,
	output signed [31:0]Pr,
	output signed [31:0]Pi);

assign Pr = (Xr*Yr)-(Xi*Yi);
assign Pi = (Xr*Yi)+(Xi*Yr);
endmodule

fft4.v
// Code your design here
module fft_n4(
	input [31:0]Ar,
	input [31:0]Ai,
	input [31:0]Br,
	input [31:0]Bi,
	input [31:0]Cr,
	input [31:0]Ci,
	input [31:0]Dr,
	input [31:0]Di,
	output [31:0]Xr0,
	output [31:0]Xr1,
	output [31:0]Xr2,
	output [31:0]Xr3,
	output [31:0]Xi0,
	output [31:0]Xi1,
	output [31:0]Xi2,
	output [31:0]Xi3);

/*
assign Xr0 = Ar+Br+Cr+Dr;
assign Xi0 = Ai+Bi+Ci+Di;
assign Xr1 = Ar+Bi-Cr-Di;
assign Xi1 = Ai-Br-Ci+Dr;
assign Xr2 = Ar-Br+Cr-Dr;
assign Xi2 = Ai-Bi+Ci-Di;
assign Xr3 = Ar-Bi-Cr+Di;
assign Xi3 = Ai+Br-Ci-Dr;
*/
/*
assign Xr0 = Ar+Cr;
assign Xi0 = Ai+Ci;
assign Xr1 = Br-Di;
assign Xi1 = Bi+Dr;
assign Xr2 = Ar-Cr;
assign Xi2 = Ai-Ci;
assign Xr3 = Br+Di;
assign Xi3 = Bi-Dr;
*/

assign Xr0 = Ar+Cr;
assign Xi0 = Ai+Ci;
assign Xr1 = Br+Dr;
assign Xi1 = Bi-Di;
assign Xr2 = Ar-Cr;
assign Xi2 = Ai-Ci;
assign Xr3 = Br-Dr;
assign Xi3 = Bi-Di;

endmodule

source/fft8.v
module fft8(
	input [31:0]A0,
	input [31:0]A1,
	input [31:0]A2,
	input [31:0]A3,
	input [31:0]A4,
	input [31:0]A5,
	input [31:0]A6,
	input [31:0]A7,
	output [31:0]Xr0,
	output [31:0]Xr1,
	output [31:0]Xr2,
	output [31:0]Xr3,
	output [31:0]Xi0,
	output [31:0]Xi1,
	output [31:0]Xi2,
	output [31:0]Xi3,
	output [31:0]Xr4,
	output [31:0]Xr5,
	output [31:0]Xr6,
	output [31:0]Xr7,
	output [31:0]Xi4,
	output [31:0]Xi5,
	output [31:0]Xi6,
	output [31:0]Xi7);

reg [31:0] sin[0:3];
reg [31:0] cos[0:3];
initial begin
	$readmemh("hexdata/sine.txt",sin);
	$readmemh("hexdata/cosine.txt",cos);
end

wire [31:0] ar0,ar1,ar2,ar3,ar4,ar5,ar6,ar7,ai0,ai1,ai2,ai3,ai4,ai5,ai6,ai7;
wire [31:0] br0,br1,br2,br3,br4,br5,br6,br7,bi0,bi1,bi2,bi3,bi4,bi5,bi6,bi7;
wire [31:0] tr0,tr1,tr2,tr3,ti0,ti1,ti2,ti3,tr4,tr5,tr6,tr7,ti4,ti5,ti6,ti7;
wire [31:0] rr3,ri3,rr7,ri7;

assign tr0 = A0 + A4;
assign tr1 = A1 + A5;
assign tr2 = A2 + A6;
assign tr3 = A3 + A7;
assign tr4 = A0 - A4;
assign tr5 = A1 - A5;
assign tr6 = A2 - A6;
assign tr7 = A3 - A7;
assign ti0 = 0;
assign ti1 = 0;
assign ti2 = 0;
assign ti3 = 0;
assign ti4 = 0;
assign ti5 = 0;
assign ti6 = 0;
assign ti7 = 0;

complex_mul m0(tr0,ti0,cos[0],sin[0],ar0,ai0);
complex_mul m1(tr1,ti1,cos[0],sin[0],ar1,ai1);
complex_mul m2(tr2,ti2,cos[0],sin[0],ar2,ai2);
complex_mul m3(tr3,ti3,cos[0],sin[0],ar3,ai3);
complex_mul m4(tr4,ti4,cos[0],sin[0],ar4,ai4);
complex_mul m5(tr5,ti5,cos[1],sin[1],ar5,ai5);
complex_mul m6(tr6,ti6,cos[2],sin[2],ar6,ai6);
complex_mul m7(tr7,ti7,cos[3],sin[3],ar7,ai7);


fft_n4 ff1(ar0,ai0,ar1,ai1,ar2,ai2,ar3,ai3,br0,bi0,br1,bi1,br2,bi2,br3,bi3);
fft_n4 ff2(ar4,ai4,ar5,ai5,ar6,ai6,ar7,ai7,br4,bi4,br5,bi5,br6,bi6,br7,bi7);

/*
assign br0 = ar0 + ar2;
assign br1 = ar1 + ar3;
assign br2 = ar0 - ar2;
assign br3 = ar1 - ar3;
assign br4 = ar4 + ar6;
assign br5 = ar5 + ar7;
assign br6 = ar4 - ar6;
assign br7 = ar5 - ar7;
assign bi0 = ai0 + ai2;
assign bi1 = ai1 + ai3;
assign bi2 = ai0 - ai2;
assign bi3 = ai1 - ai3;
assign bi4 = ai4 + ai6;
assign bi5 = ai5 + ai7;
assign bi6 = ai4 - ai6;
assign bi7 = ai5 - ai7;
*/
complex_mul n1(br3,bi3,0,32'b11111111111111111111111111111111,rr3,ri3);
complex_mul n2(br7,bi7,0,32'b11111111111111111111111111111111,rr7,ri7);

fft2 f1(br0,bi0,br1,bi1,Xr0,Xi0,Xr4,Xi4);
fft2 f2(br2,bi2,rr3,ri3,Xr2,Xi2,Xr6,Xi6);
fft2 f3(br4,bi4,br5,bi5,Xr1,Xi1,Xr5,Xi5);
fft2 f4(br6,bi6,rr7,ri7,Xr3,Xi3,Xr7,Xi7);


endmodule

source/sendSig.v
module sendSignal(
	input clk,
	input[31:0] data,
	output[31:0] Xr0,
	output[31:0] Xr1,
	output[31:0] Xr2,
	output[31:0] Xr3,
	output[31:0] Xr4,
	output[31:0] Xr5,
	output[31:0] Xr6,
	output[31:0] Xr7,
	output[31:0] Xi0,
	output[31:0] Xi1,
	output[31:0] Xi2,
	output[31:0] Xi3,
	output[31:0] Xi4,
	output[31:0] Xi5,
	output[31:0] Xi6,
	output[31:0] Xi7
	);

reg[31:0] A0,A1,A2,A3,A4,A5,A6,A7;
always @ (posedge clk)
begin
	A7 <= A6;
	A6 <= A5;
	A5 <= A4;
	A4 <= A3;
	A3 <= A2;
	A2 <= A1;
	A1 <= A0;
	A0 <= data;
	
end
fft8 ff(A0,A1,A2,A3,A4,A5,A6,A7,Xr0,Xr1,Xr2,Xr3,Xi0,Xi1,Xi2,Xi3,Xr4,Xr5,Xr6,Xr7,Xi4,Xi5,Xi6,Xi7);	
endmodule

test/serial_ip_tb.v
module serial_ip_test_bench;
reg clk;
reg[31:0] data;
wire[31:0] Xr0,Xr1,Xr2,Xr3,Xr4,Xr5,Xr6,Xr7;
wire[31:0] Xi0,Xi1,Xi2,Xi3,Xi4,Xi5,Xi6,Xi7;

sendSignal DUT(clk,data,Xr0,Xr1,Xr2,Xr3,Xr4,Xr5,Xr6,Xr7,Xi0,Xi1,Xi2,Xi3,Xi4,Xi5,Xi6,Xi7);
initial begin
	clk = 0;
	forever #5 clk=~clk;
end
initial begin
	$monitor(data,"\n",Xr0,"  ",Xr1,"  ",Xr2,"  ",Xr3,"  ",Xr4,"  ",Xr5,"  ",Xr6,"  ",Xr7,"\n",
		Xi0,"  ",Xi1,"  ",Xi2,"  ",Xi3,"  ",Xi4,"  ",Xi5,"  ",Xi6,"  ",Xi7);
	$dumpfile("dump.vcd");$dumpvars;
	data = 10;
	#10 data = 1;
	#10 data = 10;
	#10 data = 1;
	#10 data = 10;
	#10 data = 1;
	#10 data = 10;
	#10 data = 1;
	#10 data = 10;
	#10 data = 1;
	#10 data = 10;
	#10 data = 1;
	#10 data = 10;
	#10 data = 1;
	#10 data = 10;
	$finish;
end
endmodule

dump.vcd
$date
	Thu Sep 30 16:32:52 2021
$end
$version
	Icarus Verilog
$end
$timescale
	1s
$end
$scope module serial_ip_test_bench $end
$var wire 32 ! Xr7 [31:0] $end
$var wire 32 " Xr6 [31:0] $end
$var wire 32 # Xr5 [31:0] $end
$var wire 32 $ Xr4 [31:0] $end
$var wire 32 % Xr3 [31:0] $end
$var wire 32 & Xr2 [31:0] $end
$var wire 32 ' Xr1 [31:0] $end
$var wire 32 ( Xr0 [31:0] $end
$var wire 32 ) Xi7 [31:0] $end
$var wire 32 * Xi6 [31:0] $end
$var wire 32 + Xi5 [31:0] $end
$var wire 32 , Xi4 [31:0] $end
$var wire 32 - Xi3 [31:0] $end
$var wire 32 . Xi2 [31:0] $end
$var wire 32 / Xi1 [31:0] $end
$var wire 32 0 Xi0 [31:0] $end
$var reg 1 1 clk $end
$var reg 32 2 data [31:0] $end
$scope module DUT $end
$var wire 1 1 clk $end
$var wire 32 3 data [31:0] $end
$var wire 32 4 Xr7 [31:0] $end
$var wire 32 5 Xr6 [31:0] $end
$var wire 32 6 Xr5 [31:0] $end
$var wire 32 7 Xr4 [31:0] $end
$var wire 32 8 Xr3 [31:0] $end
$var wire 32 9 Xr2 [31:0] $end
$var wire 32 : Xr1 [31:0] $end
$var wire 32 ; Xr0 [31:0] $end
$var wire 32 < Xi7 [31:0] $end
$var wire 32 = Xi6 [31:0] $end
$var wire 32 > Xi5 [31:0] $end
$var wire 32 ? Xi4 [31:0] $end
$var wire 32 @ Xi3 [31:0] $end
$var wire 32 A Xi2 [31:0] $end
$var wire 32 B Xi1 [31:0] $end
$var wire 32 C Xi0 [31:0] $end
$var reg 32 D A0 [31:0] $end
$var reg 32 E A1 [31:0] $end
$var reg 32 F A2 [31:0] $end
$var reg 32 G A3 [31:0] $end
$var reg 32 H A4 [31:0] $end
$var reg 32 I A5 [31:0] $end
$var reg 32 J A6 [31:0] $end
$var reg 32 K A7 [31:0] $end
$scope module ff $end
$var wire 32 L A0 [31:0] $end
$var wire 32 M A1 [31:0] $end
$var wire 32 N A2 [31:0] $end
$var wire 32 O A3 [31:0] $end
$var wire 32 P A4 [31:0] $end
$var wire 32 Q A5 [31:0] $end
$var wire 32 R A6 [31:0] $end
$var wire 32 S A7 [31:0] $end
$var wire 32 T ti0 [31:0] $end
$var wire 32 U ti1 [31:0] $end
$var wire 32 V ti2 [31:0] $end
$var wire 32 W ti3 [31:0] $end
$var wire 32 X ti4 [31:0] $end
$var wire 32 Y ti5 [31:0] $end
$var wire 32 Z ti6 [31:0] $end
$var wire 32 [ ti7 [31:0] $end
$var wire 32 \ tr7 [31:0] $end
$var wire 32 ] tr6 [31:0] $end
$var wire 32 ^ tr5 [31:0] $end
$var wire 32 _ tr4 [31:0] $end
$var wire 32 ` tr3 [31:0] $end
$var wire 32 a tr2 [31:0] $end
$var wire 32 b tr1 [31:0] $end
$var wire 32 c tr0 [31:0] $end
$var wire 32 d rr7 [31:0] $end
$var wire 32 e rr3 [31:0] $end
$var wire 32 f ri7 [31:0] $end
$var wire 32 g ri3 [31:0] $end
$var wire 32 h br7 [31:0] $end
$var wire 32 i br6 [31:0] $end
$var wire 32 j br5 [31:0] $end
$var wire 32 k br4 [31:0] $end
$var wire 32 l br3 [31:0] $end
$var wire 32 m br2 [31:0] $end
$var wire 32 n br1 [31:0] $end
$var wire 32 o br0 [31:0] $end
$var wire 32 p bi7 [31:0] $end
$var wire 32 q bi6 [31:0] $end
$var wire 32 r bi5 [31:0] $end
$var wire 32 s bi4 [31:0] $end
$var wire 32 t bi3 [31:0] $end
$var wire 32 u bi2 [31:0] $end
$var wire 32 v bi1 [31:0] $end
$var wire 32 w bi0 [31:0] $end
$var wire 32 x ar7 [31:0] $end
$var wire 32 y ar6 [31:0] $end
$var wire 32 z ar5 [31:0] $end
$var wire 32 { ar4 [31:0] $end
$var wire 32 | ar3 [31:0] $end
$var wire 32 } ar2 [31:0] $end
$var wire 32 ~ ar1 [31:0] $end
$var wire 32 !" ar0 [31:0] $end
$var wire 32 "" ai7 [31:0] $end
$var wire 32 #" ai6 [31:0] $end
$var wire 32 $" ai5 [31:0] $end
$var wire 32 %" ai4 [31:0] $end
$var wire 32 &" ai3 [31:0] $end
$var wire 32 '" ai2 [31:0] $end
$var wire 32 (" ai1 [31:0] $end
$var wire 32 )" ai0 [31:0] $end
$var wire 32 *" Xr7 [31:0] $end
$var wire 32 +" Xr6 [31:0] $end
$var wire 32 ," Xr5 [31:0] $end
$var wire 32 -" Xr4 [31:0] $end
$var wire 32 ." Xr3 [31:0] $end
$var wire 32 /" Xr2 [31:0] $end
$var wire 32 0" Xr1 [31:0] $end
$var wire 32 1" Xr0 [31:0] $end
$var wire 32 2" Xi7 [31:0] $end
$var wire 32 3" Xi6 [31:0] $end
$var wire 32 4" Xi5 [31:0] $end
$var wire 32 5" Xi4 [31:0] $end
$var wire 32 6" Xi3 [31:0] $end
$var wire 32 7" Xi2 [31:0] $end
$var wire 32 8" Xi1 [31:0] $end
$var wire 32 9" Xi0 [31:0] $end
$scope module f1 $end
$var wire 32 :" yr [31:0] $end
$var wire 32 ;" yi [31:0] $end
$var wire 32 <" xr [31:0] $end
$var wire 32 =" xi [31:0] $end
$var wire 32 >" Yr [31:0] $end
$var wire 32 ?" Yi [31:0] $end
$var wire 32 @" Xr [31:0] $end
$var wire 32 A" Xi [31:0] $end
$upscope $end
$scope module f2 $end
$var wire 32 B" yr [31:0] $end
$var wire 32 C" yi [31:0] $end
$var wire 32 D" xr [31:0] $end
$var wire 32 E" xi [31:0] $end
$var wire 32 F" Yr [31:0] $end
$var wire 32 G" Yi [31:0] $end
$var wire 32 H" Xr [31:0] $end
$var wire 32 I" Xi [31:0] $end
$upscope $end
$scope module f3 $end
$var wire 32 J" yr [31:0] $end
$var wire 32 K" yi [31:0] $end
$var wire 32 L" xr [31:0] $end
$var wire 32 M" xi [31:0] $end
$var wire 32 N" Yr [31:0] $end
$var wire 32 O" Yi [31:0] $end
$var wire 32 P" Xr [31:0] $end
$var wire 32 Q" Xi [31:0] $end
$upscope $end
$scope module f4 $end
$var wire 32 R" yr [31:0] $end
$var wire 32 S" yi [31:0] $end
$var wire 32 T" xr [31:0] $end
$var wire 32 U" xi [31:0] $end
$var wire 32 V" Yr [31:0] $end
$var wire 32 W" Yi [31:0] $end
$var wire 32 X" Xr [31:0] $end
$var wire 32 Y" Xi [31:0] $end
$upscope $end
$scope module ff1 $end
$var wire 32 Z" Xr3 [31:0] $end
$var wire 32 [" Xr2 [31:0] $end
$var wire 32 \" Xr1 [31:0] $end
$var wire 32 ]" Xr0 [31:0] $end
$var wire 32 ^" Xi3 [31:0] $end
$var wire 32 _" Xi2 [31:0] $end
$var wire 32 `" Xi1 [31:0] $end
$var wire 32 a" Xi0 [31:0] $end
$var wire 32 b" Dr [31:0] $end
$var wire 32 c" Di [31:0] $end
$var wire 32 d" Cr [31:0] $end
$var wire 32 e" Ci [31:0] $end
$var wire 32 f" Br [31:0] $end
$var wire 32 g" Bi [31:0] $end
$var wire 32 h" Ar [31:0] $end
$var wire 32 i" Ai [31:0] $end
$upscope $end
$scope module ff2 $end
$var wire 32 j" Xr3 [31:0] $end
$var wire 32 k" Xr2 [31:0] $end
$var wire 32 l" Xr1 [31:0] $end
$var wire 32 m" Xr0 [31:0] $end
$var wire 32 n" Xi3 [31:0] $end
$var wire 32 o" Xi2 [31:0] $end
$var wire 32 p" Xi1 [31:0] $end
$var wire 32 q" Xi0 [31:0] $end
$var wire 32 r" Dr [31:0] $end
$var wire 32 s" Di [31:0] $end
$var wire 32 t" Cr [31:0] $end
$var wire 32 u" Ci [31:0] $end
$var wire 32 v" Br [31:0] $end
$var wire 32 w" Bi [31:0] $end
$var wire 32 x" Ar [31:0] $end
$var wire 32 y" Ai [31:0] $end
$upscope $end
$scope module m0 $end
$var wire 32 z" Xi [31:0] $end
$var wire 32 {" Xr [31:0] $end
$var wire 32 |" Yi [31:0] $end
$var wire 32 }" Yr [31:0] $end
$var wire 32 ~" Pr [31:0] $end
$var wire 32 !# Pi [31:0] $end
$upscope $end
$scope module m1 $end
$var wire 32 "# Xi [31:0] $end
$var wire 32 ## Xr [31:0] $end
$var wire 32 $# Yi [31:0] $end
$var wire 32 %# Yr [31:0] $end
$var wire 32 &# Pr [31:0] $end
$var wire 32 '# Pi [31:0] $end
$upscope $end
$scope module m2 $end
$var wire 32 (# Xi [31:0] $end
$var wire 32 )# Xr [31:0] $end
$var wire 32 *# Yi [31:0] $end
$var wire 32 +# Yr [31:0] $end
$var wire 32 ,# Pr [31:0] $end
$var wire 32 -# Pi [31:0] $end
$upscope $end
$scope module m3 $end
$var wire 32 .# Xi [31:0] $end
$var wire 32 /# Xr [31:0] $end
$var wire 32 0# Yi [31:0] $end
$var wire 32 1# Yr [31:0] $end
$var wire 32 2# Pr [31:0] $end
$var wire 32 3# Pi [31:0] $end
$upscope $end
$scope module m4 $end
$var wire 32 4# Xi [31:0] $end
$var wire 32 5# Xr [31:0] $end
$var wire 32 6# Yi [31:0] $end
$var wire 32 7# Yr [31:0] $end
$var wire 32 8# Pr [31:0] $end
$var wire 32 9# Pi [31:0] $end
$upscope $end
$scope module m5 $end
$var wire 32 :# Xi [31:0] $end
$var wire 32 ;# Xr [31:0] $end
$var wire 32 <# Yi [31:0] $end
$var wire 32 =# Yr [31:0] $end
$var wire 32 ># Pr [31:0] $end
$var wire 32 ?# Pi [31:0] $end
$upscope $end
$scope module m6 $end
$var wire 32 @# Xi [31:0] $end
$var wire 32 A# Xr [31:0] $end
$var wire 32 B# Yi [31:0] $end
$var wire 32 C# Yr [31:0] $end
$var wire 32 D# Pr [31:0] $end
$var wire 32 E# Pi [31:0] $end
$upscope $end
$scope module m7 $end
$var wire 32 F# Xi [31:0] $end
$var wire 32 G# Xr [31:0] $end
$var wire 32 H# Yi [31:0] $end
$var wire 32 I# Yr [31:0] $end
$var wire 32 J# Pr [31:0] $end
$var wire 32 K# Pi [31:0] $end
$upscope $end
$scope module n1 $end
$var wire 32 L# Xi [31:0] $end
$var wire 32 M# Xr [31:0] $end
$var wire 32 N# Yi [31:0] $end
$var wire 32 O# Yr [31:0] $end
$var wire 32 P# Pr [31:0] $end
$var wire 32 Q# Pi [31:0] $end
$upscope $end
$scope module n2 $end
$var wire 32 R# Xi [31:0] $end
$var wire 32 S# Xr [31:0] $end
$var wire 32 T# Yi [31:0] $end
$var wire 32 U# Yr [31:0] $end
$var wire 32 V# Pr [31:0] $end
$var wire 32 W# Pi [31:0] $end
$upscope $end
$upscope $end
$upscope $end
$upscope $end
$enddefinitions $end
#0
$dumpvars
bx W#
bx V#
b0 U#
b11111111111111111111111111111111 T#
bx S#
bx R#
bx Q#
bx P#
b0 O#
b11111111111111111111111111111111 N#
bx M#
bx L#
bx K#
bx J#
b11111111111111111111111110111001 I#
b11111111111111111111111110111001 H#
bx G#
b0 F#
bx E#
bx D#
b0 C#
b11111111111111111111111110011100 B#
bx A#
b0 @#
bx ?#
bx >#
b1000110 =#
b11111111111111111111111110111001 <#
bx ;#
b0 :#
bx 9#
bx 8#
b1100100 7#
b0 6#
bx 5#
b0 4#
bx 3#
bx 2#
b1100100 1#
b0 0#
bx /#
b0 .#
bx -#
bx ,#
b1100100 +#
b0 *#
bx )#
b0 (#
bx '#
bx &#
b1100100 %#
b0 $#
bx ##
b0 "#
bx !#
bx ~"
b1100100 }"
b0 |"
bx {"
b0 z"
bx y"
bx x"
bx w"
bx v"
bx u"
bx t"
bx s"
bx r"
bx q"
bx p"
bx o"
bx n"
bx m"
bx l"
bx k"
bx j"
bx i"
bx h"
bx g"
bx f"
bx e"
bx d"
bx c"
bx b"
bx a"
bx `"
bx _"
bx ^"
bx ]"
bx \"
bx ["
bx Z"
bx Y"
bx X"
bx W"
bx V"
bx U"
bx T"
bx S"
bx R"
bx Q"
bx P"
bx O"
bx N"
bx M"
bx L"
bx K"
bx J"
bx I"
bx H"
bx G"
bx F"
bx E"
bx D"
bx C"
bx B"
bx A"
bx @"
bx ?"
bx >"
bx ="
bx <"
bx ;"
bx :"
bx 9"
bx 8"
bx 7"
bx 6"
bx 5"
bx 4"
bx 3"
bx 2"
bx 1"
bx 0"
bx /"
bx ."
bx -"
bx ,"
bx +"
bx *"
bx )"
bx ("
bx '"
bx &"
bx %"
bx $"
bx #"
bx ""
bx !"
bx ~
bx }
bx |
bx {
bx z
bx y
bx x
bx w
bx v
bx u
bx t
bx s
bx r
bx q
bx p
bx o
bx n
bx m
bx l
bx k
bx j
bx i
bx h
bx g
bx f
bx e
bx d
bx c
bx b
bx a
bx `
bx _
bx ^
bx ]
bx \
b0 [
b0 Z
b0 Y
b0 X
b0 W
b0 V
b0 U
b0 T
bx S
bx R
bx Q
bx P
bx O
bx N
bx M
bx L
bx K
bx J
bx I
bx H
bx G
bx F
bx E
bx D
bx C
bx B
bx A
bx @
bx ?
bx >
bx =
bx <
bx ;
bx :
bx 9
bx 8
bx 7
bx 6
bx 5
bx 4
b1010 3
b1010 2
01
bx 0
bx /
bx .
bx -
bx ,
bx +
bx *
bx )
bx (
bx '
bx &
bx %
bx $
bx #
bx "
bx !
$end
#5
b1010 D
b1010 L
11
#10
01
b1 2
b1 3
#15
b1 D
b1 L
b1010 E
b1010 M
11
#20
01
b1010 2
b1010 3
#25
b1010 D
b1010 L
b1 E
b1 M
b1010 F
b1010 N
11
#30
01
b1 2
b1 3
#35
b1 D
b1 L
b1010 E
b1010 M
b1 F
b1 N
b1010 G
b1010 O
11
#40
01
b1010 2
b1010 3
#45
b1010 D
b1010 L
b1 E
b1 M
b1010 F
b1010 N
b1 G
b1 O
b11111010000 !"
b11111010000 h"
b11111010000 ~"
b0 )"
b0 i"
b0 !#
b10100 c
b10100 {"
b0 {
b0 x"
b0 8#
b0 %"
b0 y"
b0 9#
b0 _
b0 5#
b1010 H
b1010 P
11
#50
01
b1 2
b1 3
#55
b1 D
b1 L
b1010 E
b1010 M
b1 F
b1 N
b1010 G
b1010 O
b11001000 !"
b11001000 h"
b11001000 ~"
b10 c
b10 {"
b0 {
b0 x"
b0 8#
b0 _
b0 5#
b1 H
b1 P
b11111010000 ~
b11111010000 f"
b11111010000 &#
b0 ("
b0 g"
b0 '#
b10100 b
b10100 ##
b0 z
b0 v"
b0 >#
b0 $"
b0 w"
b0 ?#
b0 ^
b0 ;#
b1010 I
b1010 Q
11
#60
01
b1010 2
b1010 3
#65
b1010 D
b1010 L
b1 E
b1 M
b1010 F
b1010 N
b1 G
b1 O
b11111010000 !"
b11111010000 h"
b11111010000 ~"
b10100 c
b10100 {"
b0 {
b0 x"
b0 8#
b0 _
b0 5#
b1010 H
b1010 P
b11001000 ~
b11001000 f"
b11001000 &#
b10 b
b10 ##
b0 z
b0 v"
b0 >#
b0 $"
b0 w"
b0 ?#
b0 ^
b0 ;#
b1 I
b1 Q
b0 m
b0 D"
b0 ["
b111110100000 o
b111110100000 <"
b111110100000 ]"
b11111010000 }
b11111010000 d"
b11111010000 ,#
b0 u
b0 E"
b0 _"
b0 w
b0 ="
b0 a"
b0 '"
b0 e"
b0 -#
b10100 a
b10100 )#
b0 i
b0 T"
b0 k"
b0 k
b0 L"
b0 m"
b0 y
b0 t"
b0 D#
b0 q
b0 U"
b0 o"
b0 s
b0 M"
b0 q"
b0 #"
b0 u"
b0 E#
b0 ]
b0 A#
b1010 J
b1010 R
11
#70
01
b1 2
b1 3
#75
b1 D
b1 L
b1010 E
b1010 M
b1 F
b1 N
b1010 G
b1010 O
b11001000 !"
b11001000 h"
b11001000 ~"
b10 c
b10 {"
b0 i
b0 T"
b0 k"
b0 k
b0 L"
b0 m"
b0 {
b0 x"
b0 8#
b0 _
b0 5#
b1 H
b1 P
b11111010000 ~
b11111010000 f"
b11111010000 &#
b10100 b
b10100 ##
b0 z
b0 v"
b0 >#
b0 $"
b0 w"
b0 ?#
b0 ^
b0 ;#
b1010 I
b1010 Q
b0 m
b0 D"
b0 ["
b110010000 o
b110010000 <"
b110010000 ]"
b11001000 }
b11001000 d"
b11001000 ,#
b10 a
b10 )#
b0 q
b0 U"
b0 o"
b0 s
b0 M"
b0 q"
b0 #"
b0 u"
b0 E#
b0 ]
b0 A#
b1 J
b1 R
b0 "
b0 5
b0 +"
b0 F"
b0 &
b0 9
b0 /"
b0 H"
b0 e
b0 B"
b0 P#
b0 *
b0 =
b0 3"
b0 G"
b0 .
b0 A
b0 7"
b0 I"
b0 g
b0 C"
b0 Q#
b0 l
b0 Z"
b0 M#
b11111111111111111111000111110000 $
b11111111111111111111000111110000 7
b11111111111111111111000111110000 -"
b11111111111111111111000111110000 >"
b1000100110000 (
b1000100110000 ;
b1000100110000 1"
b1000100110000 @"
b111110100000 n
b111110100000 :"
b111110100000 \"
b11111010000 |
b11111010000 b"
b11111010000 2#
b0 t
b0 ^"
b0 L#
b0 ,
b0 ?
b0 5"
b0 ?"
b0 0
b0 C
b0 9"
b0 A"
b0 v
b0 ;"
b0 `"
b0 &"
b0 c"
b0 3#
b10100 `
b10100 /#
b0 !
b0 4
b0 *"
b0 V"
b0 %
b0 8
b0 ."
b0 X"
b0 d
b0 R"
b0 V#
b0 )
b0 <
b0 2"
b0 W"
b0 -
b0 @
b0 6"
b0 Y"
b0 f
b0 S"
b0 W#
b0 h
b0 j"
b0 S#
b0 #
b0 6
b0 ,"
b0 N"
b0 '
b0 :
b0 0"
b0 P"
b0 j
b0 J"
b0 l"
b0 x
b0 r"
b0 J#
b0 p
b0 n"
b0 R#
b0 +
b0 >
b0 4"
b0 O"
b0 /
b0 B
b0 8"
b0 Q"
b0 r
b0 K"
b0 p"
b0 ""
b0 s"
b0 K#
b0 \
b0 G#
b1010 K
b1010 S
11
#80
01
b1010 2
b1010 3
#85
b1010 D
b1010 L
b1 E
b1 M
b1010 F
b1010 N
b1 G
b1 O
b11111010000 !"
b11111010000 h"
b11111010000 ~"
b10100 c
b10100 {"
b0 i
b0 T"
b0 k"
b0 k
b0 L"
b0 m"
b0 {
b0 x"
b0 8#
b0 _
b0 5#
b1010 H
b1010 P
b11001000 ~
b11001000 f"
b11001000 &#
b10 b
b10 ##
b0 z
b0 v"
b0 >#
b0 $"
b0 w"
b0 ?#
b0 ^
b0 ;#
b1 I
b1 Q
b0 "
b0 5
b0 +"
b0 F"
b0 &
b0 9
b0 /"
b0 H"
b0 m
b0 D"
b0 ["
b111110100000 o
b111110100000 <"
b111110100000 ]"
b11111010000 }
b11111010000 d"
b11111010000 ,#
b10100 a
b10100 )#
b0 q
b0 U"
b0 o"
b0 s
b0 M"
b0 q"
b0 #"
b0 u"
b0 E#
b0 ]
b0 A#
b1010 J
b1010 R
b0 *
b0 =
b0 3"
b0 G"
b0 .
b0 A
b0 7"
b0 I"
b0 g
b0 C"
b0 Q#
b0 l
b0 Z"
b0 M#
b111000010000 $
b111000010000 7
b111000010000 -"
b111000010000 >"
b1000100110000 (
b1000100110000 ;
b1000100110000 1"
b1000100110000 @"
b110010000 n
b110010000 :"
b110010000 \"
b11001000 |
b11001000 b"
b11001000 2#
b10 `
b10 /#
b0 )
b0 <
b0 2"
b0 W"
b0 -
b0 @
b0 6"
b0 Y"
b0 f
b0 S"
b0 W#
b0 h
b0 j"
b0 S#
b0 #
b0 6
b0 ,"
b0 N"
b0 '
b0 :
b0 0"
b0 P"
b0 j
b0 J"
b0 l"
b0 x
b0 r"
b0 J#
b0 !
b0 4
b0 *"
b0 V"
b0 %
b0 8
b0 ."
b0 X"
b0 d
b0 R"
b0 V#
b0 p
b0 n"
b0 R#
b0 +
b0 >
b0 4"
b0 O"
b0 /
b0 B
b0 8"
b0 Q"
b0 r
b0 K"
b0 p"
b0 ""
b0 s"
b0 K#
b0 \
b0 G#
b1 K
b1 S
11
#90
01
b1 2
b1 3
#95
b1 D
b1 L
b1010 E
b1010 M
b1 F
b1 N
b1010 G
b1010 O
b11001000 !"
b11001000 h"
b11001000 ~"
b10 c
b10 {"
b0 i
b0 T"
b0 k"
b0 k
b0 L"
b0 m"
b0 {
b0 x"
b0 8#
b0 _
b0 5#
b1 H
b1 P
b11111010000 ~
b11111010000 f"
b11111010000 &#
b10100 b
b10100 ##
b0 z
b0 v"
b0 >#
b0 $"
b0 w"
b0 ?#
b0 ^
b0 ;#
b1010 I
b1010 Q
b0 "
b0 5
b0 +"
b0 F"
b0 &
b0 9
b0 /"
b0 H"
b0 m
b0 D"
b0 ["
b110010000 o
b110010000 <"
b110010000 ]"
b11001000 }
b11001000 d"
b11001000 ,#
b10 a
b10 )#
b0 q
b0 U"
b0 o"
b0 s
b0 M"
b0 q"
b0 #"
b0 u"
b0 E#
b0 ]
b0 A#
b1 J
b1 R
b0 *
b0 =
b0 3"
b0 G"
b0 .
b0 A
b0 7"
b0 I"
b0 g
b0 C"
b0 Q#
b0 l
b0 Z"
b0 M#
b11111111111111111111000111110000 $
b11111111111111111111000111110000 7
b11111111111111111111000111110000 -"
b11111111111111111111000111110000 >"
b1000100110000 (
b1000100110000 ;
b1000100110000 1"
b1000100110000 @"
b111110100000 n
b111110100000 :"
b111110100000 \"
b11111010000 |
b11111010000 b"
b11111010000 2#
b10100 `
b10100 /#
b0 )
b0 <
b0 2"
b0 W"
b0 -
b0 @
b0 6"
b0 Y"
b0 f
b0 S"
b0 W#
b0 h
b0 j"
b0 S#
b0 #
b0 6
b0 ,"
b0 N"
b0 '
b0 :
b0 0"
b0 P"
b0 j
b0 J"
b0 l"
b0 x
b0 r"
b0 J#
b0 !
b0 4
b0 *"
b0 V"
b0 %
b0 8
b0 ."
b0 X"
b0 d
b0 R"
b0 V#
b0 p
b0 n"
b0 R#
b0 +
b0 >
b0 4"
b0 O"
b0 /
b0 B
b0 8"
b0 Q"
b0 r
b0 K"
b0 p"
b0 ""
b0 s"
b0 K#
b0 \
b0 G#
b1010 K
b1010 S
11
#100
01
b1010 2
b1010 3
