source/fft2.v
module fft2(
	input [31:0]xr,
	input [31:0]xi,
	input [31:0]yr,
	input [31:0]yi,
	output [31:0]Xr,
	output [31:0]Xi,
	output [31:0]Yr,
	output [31:0]Yi);

assign Xr = xr + yr;
assign Yr = xr - yr;
assign Xi = xi + yi;
assign Yi = xi - yi;
endmodule

source/complex_mul.v
module complex_mul(
	input [31:0]Xr,
	input [31:0]Xi,
	input [31:0]Yr,
	input [31:0]Yi,
	output [31:0]Pr,
	output [31:0]Pi);

assign Pr = (Xr*Yr)-(Xi*Yi);
assign Pi = (Xr*Yi)+(Xi*Yr);
endmodule

fft4.v
// Code your design here
module fft_n4(
	input [31:0]Ar,
	input [31:0]Ai,
	input [31:0]Br,
	input [31:0]Bi,
	input [31:0]Cr,
	input [31:0]Ci,
	input [31:0]Dr,
	input [31:0]Di,
	output [31:0]Xr0,
	output [31:0]Xr1,
	output [31:0]Xr2,
	output [31:0]Xr3,
	output [31:0]Xi0,
	output [31:0]Xi1,
	output [31:0]Xi2,
	output [31:0]Xi3);

/*
assign Xr0 = Ar+Br+Cr+Dr;
assign Xi0 = Ai+Bi+Ci+Di;
assign Xr1 = Ar+Bi-Cr-Di;
assign Xi1 = Ai-Br-Ci+Dr;
assign Xr2 = Ar-Br+Cr-Dr;
assign Xi2 = Ai-Bi+Ci-Di;
assign Xr3 = Ar-Bi-Cr+Di;
assign Xi3 = Ai+Br-Ci-Dr;
*/
/*
assign Xr0 = Ar+Cr;
assign Xi0 = Ai+Ci;
assign Xr1 = Br-Di;
assign Xi1 = Bi+Dr;
assign Xr2 = Ar-Cr;
assign Xi2 = Ai-Ci;
assign Xr3 = Br+Di;
assign Xi3 = Bi-Dr;
*/

assign Xr0 = Ar+Cr;
assign Xi0 = Ai+Ci;
assign Xr1 = Br+Dr;
assign Xi1 = Bi-Di;
assign Xr2 = Ar-Cr;
assign Xi2 = Ai-Ci;
assign Xr3 = Br-Dr;
assign Xi3 = Bi-Di;

endmodule

source/fft8.v
module fft8(
	input [31:0]A0,
	input [31:0]A1,
	input [31:0]A2,
	input [31:0]A3,
	input [31:0]A4,
	input [31:0]A5,
	input [31:0]A6,
	input [31:0]A7,
	output [31:0]Xr0,
	output [31:0]Xr1,
	output [31:0]Xr2,
	output [31:0]Xr3,
	output [31:0]Xi0,
	output [31:0]Xi1,
	output [31:0]Xi2,
	output [31:0]Xi3,
	output [31:0]Xr4,
	output [31:0]Xr5,
	output [31:0]Xr6,
	output [31:0]Xr7,
	output [31:0]Xi4,
	output [31:0]Xi5,
	output [31:0]Xi6,
	output [31:0]Xi7);

reg [31:0] sin[0:3];
reg [31:0] cos[0:3];
initial begin
	$readmemh("hexdata/sine.txt",sin);
	$readmemh("hexdata/cosine.txt",cos);
end

wire [31:0] ar0,ar1,ar2,ar3,ar4,ar5,ar6,ar7,ai0,ai1,ai2,ai3,ai4,ai5,ai6,ai7;
wire [31:0] br0,br1,br2,br3,br4,br5,br6,br7,bi0,bi1,bi2,bi3,bi4,bi5,bi6,bi7;
wire [31:0] tr0,tr1,tr2,tr3,ti0,ti1,ti2,ti3,tr4,tr5,tr6,tr7,ti4,ti5,ti6,ti7;
wire [31:0] rr3,ri3,rr7,ri7;

assign tr0 = A0 + A4;
assign tr1 = A1 + A5;
assign tr2 = A2 + A6;
assign tr3 = A3 + A7;
assign tr4 = A0 - A4;
assign tr5 = A1 - A5;
assign tr6 = A2 - A6;
assign tr7 = A3 - A7;
assign ti0 = 0;
assign ti1 = 0;
assign ti2 = 0;
assign ti3 = 0;
assign ti4 = 0;
assign ti5 = 0;
assign ti6 = 0;
assign ti7 = 0;

complex_mul m0(tr0,ti0,cos[0],sin[0],ar0,ai0);
complex_mul m1(tr1,ti1,cos[0],sin[0],ar1,ai1);
complex_mul m2(tr2,ti2,cos[0],sin[0],ar2,ai2);
complex_mul m3(tr3,ti3,cos[0],sin[0],ar3,ai3);
complex_mul m4(tr4,ti4,cos[0],sin[0],ar4,ai4);
complex_mul m5(tr5,ti5,cos[1],sin[1],ar5,ai5);
complex_mul m6(tr6,ti6,cos[2],sin[2],ar6,ai6);
complex_mul m7(tr7,ti7,cos[3],sin[3],ar7,ai7);


fft_n4 ff1(ar0,ai0,ar1,ai1,ar2,ai2,ar3,ai3,br0,bi0,br1,bi1,br2,bi2,br3,bi3);
fft_n4 ff2(ar4,ai4,ar5,ai5,ar6,ai6,ar7,ai7,br4,bi4,br5,bi5,br6,bi6,br7,bi7);

/*
assign br0 = ar0 + ar2;
assign br1 = ar1 + ar3;
assign br2 = ar0 - ar2;
assign br3 = ar1 - ar3;
assign br4 = ar4 + ar6;
assign br5 = ar5 + ar7;
assign br6 = ar4 - ar6;
assign br7 = ar5 - ar7;
assign bi0 = ai0 + ai2;
assign bi1 = ai1 + ai3;
assign bi2 = ai0 - ai2;
assign bi3 = ai1 - ai3;
assign bi4 = ai4 + ai6;
assign bi5 = ai5 + ai7;
assign bi6 = ai4 - ai6;
assign bi7 = ai5 - ai7;
*/
complex_mul n1(br3,bi3,0,32'b11111111111111111111111111111111,rr3,ri3);
complex_mul n2(br7,bi7,0,32'b11111111111111111111111111111111,rr7,ri7);

fft2 f1(br0,bi0,br1,bi1,Xr0,Xi0,Xr4,Xi4);
fft2 f2(br2,bi2,rr3,ri3,Xr2,Xi2,Xr6,Xi6);
fft2 f3(br4,bi4,br5,bi5,Xr1,Xi1,Xr5,Xi5);
fft2 f4(br6,bi6,rr7,ri7,Xr3,Xi3,Xr7,Xi7);


endmodule

source/sendSig.v
module sendSignal(
	input clk,
	input[31:0] data,
	output[31:0] Xr0,
	output[31:0] Xr1,
	output[31:0] Xr2,
	output[31:0] Xr3,
	output[31:0] Xr4,
	output[31:0] Xr5,
	output[31:0] Xr6,
	output[31:0] Xr7,
	output[31:0] Xi0,
	output[31:0] Xi1,
	output[31:0] Xi2,
	output[31:0] Xi3,
	output[31:0] Xi4,
	output[31:0] Xi5,
	output[31:0] Xi6,
	output[31:0] Xi7
	);

reg[31:0] A0,A1,A2,A3,A4,A5,A6,A7;
always @ (posedge clk)
begin
	A7 <= A6;
	A6 <= A5;
	A5 <= A4;
	A4 <= A3;
	A3 <= A2;
	A2 <= A1;
	A1 <= A0;
	A0 <= data;
	
end
fft8 ff(A0,A1,A2,A3,A4,A5,A6,A7,Xr0,Xr1,Xr2,Xr3,Xi0,Xi1,Xi2,Xi3,Xr4,Xr5,Xr6,Xr7,Xi4,Xi5,Xi6,Xi7);	
endmodule

test/gen_data_tb.v
module test_bench;
reg clk;
reg[31:0] data;
wire[31:0] Xr0,Xr1,Xr2,Xr3,Xr4,Xr5,Xr6,Xr7;
wire[31:0] Xi0,Xi1,Xi2,Xi3,Xi4,Xi5,Xi6,Xi7;
reg [31:0] gen_data[0:98];
integer i;


sendSignal DUT(clk,data,Xr0,Xr1,Xr2,Xr3,Xr4,Xr5,Xr6,Xr7,Xi0,Xi1,Xi2,Xi3,Xi4,Xi5,Xi6,Xi7);
initial begin
	$readmemh("test/Gen_data.txt",gen_data);
end
initial begin
	clk = 0;
	forever #5 clk=~clk;
end
initial begin
	$monitor(data,"\n",Xr0,"  ",Xr1,"  ",Xr2,"  ",Xr3,"  ",Xr4,"  ",Xr5,"  ",Xr6,"  ",Xr7,"\n",
		Xi0,"  ",Xi1,"  ",Xi2,"  ",Xi3,"  ",Xi4,"  ",Xi5,"  ",Xi6,"  ",Xi7);
	$dumpfile("dump.vcd");$dumpvars;
	for(i=0;i<100;i=i+1)
	begin
		data = gen_data[i];
		#10;
	end
	$finish;
end
endmodule

dump.vcd
$date
	Thu Oct  7 23:28:00 2021
$end
$version
	Icarus Verilog
$end
$timescale
	1s
$end
$scope module test_bench $end
$var wire 32 ! Xr7 [31:0] $end
$var wire 32 " Xr6 [31:0] $end
$var wire 32 # Xr5 [31:0] $end
$var wire 32 $ Xr4 [31:0] $end
$var wire 32 % Xr3 [31:0] $end
$var wire 32 & Xr2 [31:0] $end
$var wire 32 ' Xr1 [31:0] $end
$var wire 32 ( Xr0 [31:0] $end
$var wire 32 ) Xi7 [31:0] $end
$var wire 32 * Xi6 [31:0] $end
$var wire 32 + Xi5 [31:0] $end
$var wire 32 , Xi4 [31:0] $end
$var wire 32 - Xi3 [31:0] $end
$var wire 32 . Xi2 [31:0] $end
$var wire 32 / Xi1 [31:0] $end
$var wire 32 0 Xi0 [31:0] $end
$var reg 1 1 clk $end
$var reg 32 2 data [31:0] $end
$var integer 32 3 i [31:0] $end
$scope module DUT $end
$var wire 1 1 clk $end
$var wire 32 4 data [31:0] $end
$var wire 32 5 Xr7 [31:0] $end
$var wire 32 6 Xr6 [31:0] $end
$var wire 32 7 Xr5 [31:0] $end
$var wire 32 8 Xr4 [31:0] $end
$var wire 32 9 Xr3 [31:0] $end
$var wire 32 : Xr2 [31:0] $end
$var wire 32 ; Xr1 [31:0] $end
$var wire 32 < Xr0 [31:0] $end
$var wire 32 = Xi7 [31:0] $end
$var wire 32 > Xi6 [31:0] $end
$var wire 32 ? Xi5 [31:0] $end
$var wire 32 @ Xi4 [31:0] $end
$var wire 32 A Xi3 [31:0] $end
$var wire 32 B Xi2 [31:0] $end
$var wire 32 C Xi1 [31:0] $end
$var wire 32 D Xi0 [31:0] $end
$var reg 32 E A0 [31:0] $end
$var reg 32 F A1 [31:0] $end
$var reg 32 G A2 [31:0] $end
$var reg 32 H A3 [31:0] $end
$var reg 32 I A4 [31:0] $end
$var reg 32 J A5 [31:0] $end
$var reg 32 K A6 [31:0] $end
$var reg 32 L A7 [31:0] $end
$scope module ff $end
$var wire 32 M A0 [31:0] $end
$var wire 32 N A1 [31:0] $end
$var wire 32 O A2 [31:0] $end
$var wire 32 P A3 [31:0] $end
$var wire 32 Q A4 [31:0] $end
$var wire 32 R A5 [31:0] $end
$var wire 32 S A6 [31:0] $end
$var wire 32 T A7 [31:0] $end
$var wire 32 U ti0 [31:0] $end
$var wire 32 V ti1 [31:0] $end
$var wire 32 W ti2 [31:0] $end
$var wire 32 X ti3 [31:0] $end
$var wire 32 Y ti4 [31:0] $end
$var wire 32 Z ti5 [31:0] $end
$var wire 32 [ ti6 [31:0] $end
$var wire 32 \ ti7 [31:0] $end
$var wire 32 ] tr7 [31:0] $end
$var wire 32 ^ tr6 [31:0] $end
$var wire 32 _ tr5 [31:0] $end
$var wire 32 ` tr4 [31:0] $end
$var wire 32 a tr3 [31:0] $end
$var wire 32 b tr2 [31:0] $end
$var wire 32 c tr1 [31:0] $end
$var wire 32 d tr0 [31:0] $end
$var wire 32 e rr7 [31:0] $end
$var wire 32 f rr3 [31:0] $end
$var wire 32 g ri7 [31:0] $end
$var wire 32 h ri3 [31:0] $end
$var wire 32 i br7 [31:0] $end
$var wire 32 j br6 [31:0] $end
$var wire 32 k br5 [31:0] $end
$var wire 32 l br4 [31:0] $end
$var wire 32 m br3 [31:0] $end
$var wire 32 n br2 [31:0] $end
$var wire 32 o br1 [31:0] $end
$var wire 32 p br0 [31:0] $end
$var wire 32 q bi7 [31:0] $end
$var wire 32 r bi6 [31:0] $end
$var wire 32 s bi5 [31:0] $end
$var wire 32 t bi4 [31:0] $end
$var wire 32 u bi3 [31:0] $end
$var wire 32 v bi2 [31:0] $end
$var wire 32 w bi1 [31:0] $end
$var wire 32 x bi0 [31:0] $end
$var wire 32 y ar7 [31:0] $end
$var wire 32 z ar6 [31:0] $end
$var wire 32 { ar5 [31:0] $end
$var wire 32 | ar4 [31:0] $end
$var wire 32 } ar3 [31:0] $end
$var wire 32 ~ ar2 [31:0] $end
$var wire 32 !" ar1 [31:0] $end
$var wire 32 "" ar0 [31:0] $end
$var wire 32 #" ai7 [31:0] $end
$var wire 32 $" ai6 [31:0] $end
$var wire 32 %" ai5 [31:0] $end
$var wire 32 &" ai4 [31:0] $end
$var wire 32 '" ai3 [31:0] $end
$var wire 32 (" ai2 [31:0] $end
$var wire 32 )" ai1 [31:0] $end
$var wire 32 *" ai0 [31:0] $end
$var wire 32 +" Xr7 [31:0] $end
$var wire 32 ," Xr6 [31:0] $end
$var wire 32 -" Xr5 [31:0] $end
$var wire 32 ." Xr4 [31:0] $end
$var wire 32 /" Xr3 [31:0] $end
$var wire 32 0" Xr2 [31:0] $end
$var wire 32 1" Xr1 [31:0] $end
$var wire 32 2" Xr0 [31:0] $end
$var wire 32 3" Xi7 [31:0] $end
$var wire 32 4" Xi6 [31:0] $end
$var wire 32 5" Xi5 [31:0] $end
$var wire 32 6" Xi4 [31:0] $end
$var wire 32 7" Xi3 [31:0] $end
$var wire 32 8" Xi2 [31:0] $end
$var wire 32 9" Xi1 [31:0] $end
$var wire 32 :" Xi0 [31:0] $end
$scope module f1 $end
$var wire 32 ;" yr [31:0] $end
$var wire 32 <" yi [31:0] $end
$var wire 32 =" xr [31:0] $end
$var wire 32 >" xi [31:0] $end
$var wire 32 ?" Yr [31:0] $end
$var wire 32 @" Yi [31:0] $end
$var wire 32 A" Xr [31:0] $end
$var wire 32 B" Xi [31:0] $end
$upscope $end
$scope module f2 $end
$var wire 32 C" yr [31:0] $end
$var wire 32 D" yi [31:0] $end
$var wire 32 E" xr [31:0] $end
$var wire 32 F" xi [31:0] $end
$var wire 32 G" Yr [31:0] $end
$var wire 32 H" Yi [31:0] $end
$var wire 32 I" Xr [31:0] $end
$var wire 32 J" Xi [31:0] $end
$upscope $end
$scope module f3 $end
$var wire 32 K" yr [31:0] $end
$var wire 32 L" yi [31:0] $end
$var wire 32 M" xr [31:0] $end
$var wire 32 N" xi [31:0] $end
$var wire 32 O" Yr [31:0] $end
$var wire 32 P" Yi [31:0] $end
$var wire 32 Q" Xr [31:0] $end
$var wire 32 R" Xi [31:0] $end
$upscope $end
$scope module f4 $end
$var wire 32 S" yr [31:0] $end
$var wire 32 T" yi [31:0] $end
$var wire 32 U" xr [31:0] $end
$var wire 32 V" xi [31:0] $end
$var wire 32 W" Yr [31:0] $end
$var wire 32 X" Yi [31:0] $end
$var wire 32 Y" Xr [31:0] $end
$var wire 32 Z" Xi [31:0] $end
$upscope $end
$scope module ff1 $end
$var wire 32 [" Xr3 [31:0] $end
$var wire 32 \" Xr2 [31:0] $end
$var wire 32 ]" Xr1 [31:0] $end
$var wire 32 ^" Xr0 [31:0] $end
$var wire 32 _" Xi3 [31:0] $end
$var wire 32 `" Xi2 [31:0] $end
$var wire 32 a" Xi1 [31:0] $end
$var wire 32 b" Xi0 [31:0] $end
$var wire 32 c" Dr [31:0] $end
$var wire 32 d" Di [31:0] $end
$var wire 32 e" Cr [31:0] $end
$var wire 32 f" Ci [31:0] $end
$var wire 32 g" Br [31:0] $end
$var wire 32 h" Bi [31:0] $end
$var wire 32 i" Ar [31:0] $end
$var wire 32 j" Ai [31:0] $end
$upscope $end
$scope module ff2 $end
$var wire 32 k" Xr3 [31:0] $end
$var wire 32 l" Xr2 [31:0] $end
$var wire 32 m" Xr1 [31:0] $end
$var wire 32 n" Xr0 [31:0] $end
$var wire 32 o" Xi3 [31:0] $end
$var wire 32 p" Xi2 [31:0] $end
$var wire 32 q" Xi1 [31:0] $end
$var wire 32 r" Xi0 [31:0] $end
$var wire 32 s" Dr [31:0] $end
$var wire 32 t" Di [31:0] $end
$var wire 32 u" Cr [31:0] $end
$var wire 32 v" Ci [31:0] $end
$var wire 32 w" Br [31:0] $end
$var wire 32 x" Bi [31:0] $end
$var wire 32 y" Ar [31:0] $end
$var wire 32 z" Ai [31:0] $end
$upscope $end
$scope module m0 $end
$var wire 32 {" Xi [31:0] $end
$var wire 32 |" Xr [31:0] $end
$var wire 32 }" Yi [31:0] $end
$var wire 32 ~" Yr [31:0] $end
$var wire 32 !# Pr [31:0] $end
$var wire 32 "# Pi [31:0] $end
$upscope $end
$scope module m1 $end
$var wire 32 ## Xi [31:0] $end
$var wire 32 $# Xr [31:0] $end
$var wire 32 %# Yi [31:0] $end
$var wire 32 &# Yr [31:0] $end
$var wire 32 '# Pr [31:0] $end
$var wire 32 (# Pi [31:0] $end
$upscope $end
$scope module m2 $end
$var wire 32 )# Xi [31:0] $end
$var wire 32 *# Xr [31:0] $end
$var wire 32 +# Yi [31:0] $end
$var wire 32 ,# Yr [31:0] $end
$var wire 32 -# Pr [31:0] $end
$var wire 32 .# Pi [31:0] $end
$upscope $end
$scope module m3 $end
$var wire 32 /# Xi [31:0] $end
$var wire 32 0# Xr [31:0] $end
$var wire 32 1# Yi [31:0] $end
$var wire 32 2# Yr [31:0] $end
$var wire 32 3# Pr [31:0] $end
$var wire 32 4# Pi [31:0] $end
$upscope $end
$scope module m4 $end
$var wire 32 5# Xi [31:0] $end
$var wire 32 6# Xr [31:0] $end
$var wire 32 7# Yi [31:0] $end
$var wire 32 8# Yr [31:0] $end
$var wire 32 9# Pr [31:0] $end
$var wire 32 :# Pi [31:0] $end
$upscope $end
$scope module m5 $end
$var wire 32 ;# Xi [31:0] $end
$var wire 32 <# Xr [31:0] $end
$var wire 32 =# Yi [31:0] $end
$var wire 32 ># Yr [31:0] $end
$var wire 32 ?# Pr [31:0] $end
$var wire 32 @# Pi [31:0] $end
$upscope $end
$scope module m6 $end
$var wire 32 A# Xi [31:0] $end
$var wire 32 B# Xr [31:0] $end
$var wire 32 C# Yi [31:0] $end
$var wire 32 D# Yr [31:0] $end
$var wire 32 E# Pr [31:0] $end
$var wire 32 F# Pi [31:0] $end
$upscope $end
$scope module m7 $end
$var wire 32 G# Xi [31:0] $end
$var wire 32 H# Xr [31:0] $end
$var wire 32 I# Yi [31:0] $end
$var wire 32 J# Yr [31:0] $end
$var wire 32 K# Pr [31:0] $end
$var wire 32 L# Pi [31:0] $end
$upscope $end
$scope module n1 $end
$var wire 32 M# Xi [31:0] $end
$var wire 32 N# Xr [31:0] $end
$var wire 32 O# Yi [31:0] $end
$var wire 32 P# Yr [31:0] $end
$var wire 32 Q# Pr [31:0] $end
$var wire 32 R# Pi [31:0] $end
$upscope $end
$scope module n2 $end
$var wire 32 S# Xi [31:0] $end
$var wire 32 T# Xr [31:0] $end
$var wire 32 U# Yi [31:0] $end
$var wire 32 V# Yr [31:0] $end
$var wire 32 W# Pr [31:0] $end
$var wire 32 X# Pi [31:0] $end
$upscope $end
$upscope $end
$upscope $end
$upscope $end
$enddefinitions $end
#0
$dumpvars
bx X#
bx W#
b0 V#
b11111111111111111111111111111111 U#
bx T#
bx S#
bx R#
bx Q#
b0 P#
b11111111111111111111111111111111 O#
bx N#
bx M#
bx L#
bx K#
b11111111111111111111111110111001 J#
b11111111111111111111111110111001 I#
bx H#
b0 G#
bx F#
bx E#
b0 D#
b11111111111111111111111110011100 C#
bx B#
b0 A#
bx @#
bx ?#
b1000110 >#
b11111111111111111111111110111001 =#
bx <#
b0 ;#
bx :#
bx 9#
b1100100 8#
b0 7#
bx 6#
b0 5#
bx 4#
bx 3#
b1100100 2#
b0 1#
bx 0#
b0 /#
bx .#
bx -#
b1100100 ,#
b0 +#
bx *#
b0 )#
bx (#
bx '#
b1100100 &#
b0 %#
bx $#
b0 ##
bx "#
bx !#
b1100100 ~"
b0 }"
bx |"
b0 {"
bx z"
bx y"
bx x"
bx w"
bx v"
bx u"
bx t"
bx s"
bx r"
bx q"
bx p"
bx o"
bx n"
bx m"
bx l"
bx k"
bx j"
bx i"
bx h"
bx g"
bx f"
bx e"
bx d"
bx c"
bx b"
bx a"
bx `"
bx _"
bx ^"
bx ]"
bx \"
bx ["
bx Z"
bx Y"
bx X"
bx W"
bx V"
bx U"
bx T"
bx S"
bx R"
bx Q"
bx P"
bx O"
bx N"
bx M"
bx L"
bx K"
bx J"
bx I"
bx H"
bx G"
bx F"
bx E"
bx D"
bx C"
bx B"
bx A"
bx @"
bx ?"
bx >"
bx ="
bx <"
bx ;"
bx :"
bx 9"
bx 8"
bx 7"
bx 6"
bx 5"
bx 4"
bx 3"
bx 2"
bx 1"
bx 0"
bx /"
bx ."
bx -"
bx ,"
bx +"
bx *"
bx )"
bx ("
bx '"
bx &"
bx %"
bx $"
bx #"
bx ""
bx !"
bx ~
bx }
bx |
bx {
bx z
bx y
bx x
bx w
bx v
bx u
bx t
bx s
bx r
bx q
bx p
bx o
bx n
bx m
bx l
bx k
bx j
bx i
bx h
bx g
bx f
bx e
bx d
bx c
bx b
bx a
bx `
bx _
bx ^
bx ]
b0 \
b0 [
b0 Z
b0 Y
b0 X
b0 W
b0 V
b0 U
bx T
bx S
bx R
bx Q
bx P
bx O
bx N
bx M
bx L
bx K
bx J
bx I
bx H
bx G
bx F
bx E
bx D
bx C
bx B
bx A
bx @
bx ?
bx >
bx =
bx <
bx ;
bx :
bx 9
bx 8
bx 7
bx 6
bx 5
b1100100 4
b0 3
b1100100 2
01
bx 0
bx /
bx .
bx -
bx ,
bx +
bx *
bx )
bx (
bx '
bx &
bx %
bx $
bx #
bx "
bx !
$end
#5
b1100100 E
b1100100 M
11
#10
01
b10011111 2
b10011111 4
b1 3
#15
b10011111 E
b10011111 M
b1100100 F
b1100100 N
11
#20
01
b11000011 2
b11000011 4
b10 3
#25
b11000011 E
b11000011 M
b10011111 F
b10011111 N
b1100100 G
b1100100 O
11
#30
01
b11000010 2
b11000010 4
b11 3
#35
b11000010 E
b11000010 M
b11000011 F
b11000011 N
b10011111 G
b10011111 O
b1100100 H
b1100100 P
11
#40
01
b10011100 2
b10011100 4
b100 3
#45
b10011100 E
b10011100 M
b11000010 F
b11000010 N
b11000011 G
b11000011 O
b10011111 H
b10011111 P
b110010000000000 ""
b110010000000000 i"
b110010000000000 !#
b0 *"
b0 j"
b0 "#
b100000000 d
b100000000 |"
b1010111100000 |
b1010111100000 y"
b1010111100000 9#
b0 &"
b0 z"
b0 :#
b111000 `
b111000 6#
b1100100 I
b1100100 Q
11
#50
01
b1100000 2
b1100000 4
b101 3
#55
b1100000 E
b1100000 M
b10011100 F
b10011100 N
b11000010 G
b11000010 O
b11000011 H
b11000011 P
b110001110011100 ""
b110001110011100 i"
b110001110011100 !#
b11111111 d
b11111111 |"
b11111111111111111110011101100100 |
b11111111111111111110011101100100 y"
b11111111111111111110011101100100 9#
b11111111111111111111111111000001 `
b11111111111111111111111111000001 6#
b10011111 I
b10011111 Q
b110010000000000 !"
b110010000000000 g"
b110010000000000 '#
b0 )"
b0 h"
b0 (#
b100000000 c
b100000000 $#
b111101010000 {
b111101010000 w"
b111101010000 ?#
b11111111111111111111000001111000 %"
b11111111111111111111000001111000 x"
b11111111111111111111000001111000 @#
b111000 _
b111000 <#
b1100100 J
b1100100 R
11
#60
01
b100110 2
b100110 4
b110 3
#65
b100110 E
b100110 M
b1100000 F
b1100000 N
b10011100 G
b10011100 O
b11000010 H
b11000010 P
b101101100000100 ""
b101101100000100 i"
b101101100000100 !#
b11101001 d
b11101001 |"
b11111111111111111100001010101100 |
b11111111111111111100001010101100 y"
b11111111111111111100001010101100 9#
b11111111111111111111111101100011 `
b11111111111111111111111101100011 6#
b11000011 I
b11000011 Q
b110001110011100 !"
b110001110011100 g"
b110001110011100 '#
b11111111 c
b11111111 $#
b11111111111111111110111011000110 {
b11111111111111111110111011000110 w"
b11111111111111111110111011000110 ?#
b1000101111001 %"
b1000101111001 x"
b1000101111001 @#
b11111111111111111111111111000001 _
b11111111111111111111111111000001 <#
b10011111 J
b10011111 R
b11111111111111111111011100000100 n
b11111111111111111111011100000100 E"
b11111111111111111111011100000100 \"
b1011111100000100 p
b1011111100000100 ="
b1011111100000100 ^"
b110010000000000 ~
b110010000000000 e"
b110010000000000 -#
b0 v
b0 F"
b0 `"
b0 x
b0 >"
b0 b"
b0 ("
b0 f"
b0 .#
b100000000 b
b100000000 *#
b11111111111111111100001010101100 j
b11111111111111111100001010101100 U"
b11111111111111111100001010101100 l"
b11111111111111111100001010101100 l
b11111111111111111100001010101100 M"
b11111111111111111100001010101100 n"
b0 z
b0 u"
b0 E#
b1010111100000 r
b1010111100000 V"
b1010111100000 p"
b11111111111111111110101000100000 t
b11111111111111111110101000100000 N"
b11111111111111111110101000100000 r"
b11111111111111111110101000100000 $"
b11111111111111111110101000100000 v"
b11111111111111111110101000100000 F#
b111000 ^
b111000 B#
b1100100 K
b1100100 S
11
#70
01
b11 2
b11 4
b111 3
#75
b11 E
b11 M
b100110 F
b100110 N
b1100000 G
b1100000 O
b10011100 H
b10011100 P
b100110011110100 ""
b100110011110100 i"
b100110011110100 !#
b11000101 d
b11000101 |"
b11111111111111111011010101100100 j
b11111111111111111011010101100100 U"
b11111111111111111011010101100100 l"
b11111111111111111011010101100100 l
b11111111111111111011010101100100 M"
b11111111111111111011010101100100 n"
b11111111111111111011010101100100 |
b11111111111111111011010101100100 y"
b11111111111111111011010101100100 9#
b11111111111111111111111101000001 `
b11111111111111111111111101000001 6#
b11000010 I
b11000010 Q
b101101100000100 !"
b101101100000100 g"
b101101100000100 '#
b11101001 c
b11101001 $#
b11111111111111111101010100010010 {
b11111111111111111101010100010010 w"
b11111111111111111101010100010010 ?#
b10101110001011 %"
b10101110001011 x"
b10101110001011 @#
b11111111111111111111111101100011 _
b11111111111111111111111101100011 <#
b11000011 J
b11000011 R
b11111111111111111110100101011000 n
b11111111111111111110100101011000 E"
b11111111111111111110100101011000 \"
b1011000010010000 p
b1011000010010000 ="
b1011000010010000 ^"
b110001110011100 ~
b110001110011100 e"
b110001110011100 -#
b11111111 b
b11111111 *#
b11111111111111111110011101100100 r
b11111111111111111110011101100100 V"
b11111111111111111110011101100100 p"
b1100010011100 t
b1100010011100 N"
b1100010011100 r"
b1100010011100 $"
b1100010011100 v"
b1100010011100 F#
b11111111111111111111111111000001 ^
b11111111111111111111111111000001 B#
b10011111 K
b10011111 S
b11111111111111111110100101011000 "
b11111111111111111110100101011000 6
b11111111111111111110100101011000 ,"
b11111111111111111110100101011000 G"
b11111111111111111110100101011000 &
b11111111111111111110100101011000 :
b11111111111111111110100101011000 0"
b11111111111111111110100101011000 I"
b0 f
b0 C"
b0 Q#
b11111111111111111111011100000100 *
b11111111111111111111011100000100 >
b11111111111111111111011100000100 4"
b11111111111111111111011100000100 H"
b100011111100 .
b100011111100 B
b100011111100 8"
b100011111100 J"
b100011111100 h
b100011111100 D"
b100011111100 R#
b11111111111111111111011100000100 m
b11111111111111111111011100000100 ["
b11111111111111111111011100000100 N#
b11111111111111111111000110001100 $
b11111111111111111111000110001100 8
b11111111111111111111000110001100 ."
b11111111111111111111000110001100 ?"
b10110111110010100 (
b10110111110010100 <
b10110111110010100 2"
b10110111110010100 A"
b1011111100000100 o
b1011111100000100 ;"
b1011111100000100 ]"
b110010000000000 }
b110010000000000 c"
b110010000000000 3#
b0 u
b0 _"
b0 M#
b0 ,
b0 @
b0 6"
b0 @"
b0 0
b0 D
b0 :"
b0 B"
b0 w
b0 <"
b0 a"
b0 '"
b0 d"
b0 4#
b100000000 a
b100000000 0#
b11111111111111110111101001010001 !
b11111111111111110111101001010001 5
b11111111111111110111101001010001 +"
b11111111111111110111101001010001 W"
b11111111111111111111000001110111 %
b11111111111111111111000001110111 9
b11111111111111111111000001110111 /"
b11111111111111111111000001110111 Y"
b11101100010011 e
b11101100010011 S"
b11101100010011 W#
b11111111111111111100101111111110 )
b11111111111111111100101111111110 =
b11111111111111111100101111111110 3"
b11111111111111111100101111111110 X"
b1011001010 -
b1011001010 A
b1011001010 7"
b1011001010 Z"
b1101101100110 g
b1101101100110 T"
b1101101100110 X#
b11111111111111111110010010011010 i
b11111111111111111110010010011010 k"
b11111111111111111110010010011010 T#
b11111111111111111110111111011010 #
b11111111111111111110111111011010 7
b11111111111111111110111111011010 -"
b11111111111111111110111111011010 O"
b11111111111111110111101011101110 '
b11111111111111110111101011101110 ;
b11111111111111110111101011101110 1"
b11111111111111110111101011101110 Q"
b11111111111111111100010110001010 k
b11111111111111111100010110001010 K"
b11111111111111111100010110001010 m"
b11111111111111111111000001111000 y
b11111111111111111111000001111000 s"
b11111111111111111111000001111000 K#
b11101100010011 q
b11101100010011 o"
b11101100010011 S#
b11111111111111111111110010011001 +
b11111111111111111111110010011001 ?
b11111111111111111111110010011001 5"
b11111111111111111111110010011001 P"
b11010010011111 /
b11010010011111 C
b11010010011111 9"
b11010010011111 R"
b1110000000011 s
b1110000000011 L"
b1110000000011 q"
b11111111111111111111000001111000 #"
b11111111111111111111000001111000 t"
b11111111111111111111000001111000 L#
b111000 ]
b111000 H#
b1100100 L
b1100100 T
11
#80
01
b110 2
b110 4
b1000 3
